Metadata-Version: 2.1
Name: odoo13-addon-stock-move-line-auto-fill
Version: 13.0.1.0.2
Summary: Stock Move Line auto fill
Home-page: https://github.com/OCA/stock-logistics-workflow/
Author: ACSONE SA/NV,Tecnativa,Odoo Community Association (OCA)
Author-email: support@odoo-community.org
License: AGPL-3
Platform: UNKNOWN
Classifier: Programming Language :: Python
Classifier: Framework :: Odoo
Classifier: License :: OSI Approved :: GNU Affero General Public License v3
Requires-Python: >=3.5
Requires-Dist: odoo (<13.1dev,>=13.0a)
